bt_dualboot/__init__.py
bt_dualboot/__main__.py
bt_dualboot/__meta__.py
bt_dualboot/bluetooth_device.py
bt_dualboot/bt_linux/__init__.py
bt_dualboot/bt_linux/bluetooth_device_factory.py
bt_dualboot/bt_linux/devices.py
bt_dualboot/bt_sync_manager/__init__.py
bt_dualboot/bt_sync_manager/bt_sync_manager.py
bt_dualboot/bt_windows/__init__.py
bt_dualboot/bt_windows/convert.py
bt_dualboot/bt_windows/devices.py
bt_dualboot/cli/__init__.py
bt_dualboot/cli/__main__.py
bt_dualboot/cli/app.py
bt_dualboot/cli/tools.py
bt_dualboot/win_mount.py
bt_dualboot/windows_registry/__init__.py
bt_dualboot/windows_registry/windows_registry.py
bt_dualboot-1.0.1.dist-info/entry_points.txt
bt_dualboot-1.0.1.dist-info/WHEEL
bt_dualboot-1.0.1.dist-info/METADATA
bt_dualboot-1.0.1.dist-info/RECORD
