Metadata-Version: 2.1
Name: bt-dualboot
Version: 1.0.1
Summary: Sync Bluetooth for dualboot Linux and Windows
Home-page: https://github.com/x2es/bt-dualboot.git
License: MIT
Keywords: bluetooth,dualboot,sync,pairing,keys
Author: Konstantin Ivanov
Author-email: KEIvanov@gmail.com
Requires-Python: >=3.6,<4.0
Classifier: Development Status :: 3 - Alpha
Classifier: Environment :: Console
Classifier: Intended Audience :: End Users/Desktop
Classifier: Intended Audience :: System Administrators
Classifier: License :: OSI Approved :: MIT License
Classifier: Operating System :: POSIX :: Linux
Classifier: Programming Language :: Python :: 3
Classifier: Programming Language :: Python :: 3.10
Classifier: Programming Language :: Python :: 3.6
Classifier: Programming Language :: Python :: 3.7
Classifier: Programming Language :: Python :: 3.8
Classifier: Programming Language :: Python :: 3.9
Classifier: Topic :: Home Automation
Classifier: Topic :: Multimedia
Classifier: Topic :: System
Classifier: Topic :: System :: Operating System
Classifier: Topic :: System :: Systems Administration
Project-URL: Repository, https://github.com/x2es/bt-dualboot.git
